{
    "singular": "analyticsTableHook",
    "plural": "analyticsTableHooks",
    "name": "analyticsTableHook",
    "displayName": "Analytics Table Hook",
    "shareable": false,
    "dataShareable": false,
    "authorities": [
        { "type": "CREATE", "authorities": ["F_ANALYTICSTABLEHOOK_ADD"] },
        { "type": "DELETE", "authorities": ["F_ANALYTICSTABLEHOOK_DELETE"] }
    ],
    "properties": {
        "phase": {
            "klass": "org.hisp.dhis.analytics.AnalyticsTablePhase",
            "propertyType": "CONSTANT",
            "name": "phase",
            "fieldName": "phase",
            "persisted": true,
            "namespace": "http://dhis2.org/schema/dxf/2.0",
            "attribute": false,
            "simple": true,
            "collection": false,
            "ordered": false,
            "owner": true,
            "identifiableObject": false,
            "nameableObject": false,
            "embeddedObject": false,
            "analyticalObject": false,
            "readable": true,
            "writable": true,
            "unique": false,
            "required": true,
            "length": 50,
            "manyToMany": false,
            "oneToOne": false,
            "manyToOne": false,
            "oneToMany": false,
            "constants": [
                "RESOURCE_TABLE_POPULATED",
                "ANALYTICS_TABLE_POPULATED"
            ],
            "translatable": false,
            "gistPreferences": { "included": "AUTO", "transformation": "AUTO" },
            "sortable": true,
            "propertyTransformer": false
        },
        "favorites": {
            "klass": "java.util.Set",
            "propertyType": "COLLECTION",
            "itemKlass": "java.lang.String",
            "itemPropertyType": "TEXT",
            "name": "favorite",
            "fieldName": "favorites",
            "persisted": false,
            "collectionName": "favorites",
            "collectionWrapping": true,
            "namespace": "http://dhis2.org/schema/dxf/2.0",
            "attribute": false,
            "simple": true,
            "collection": true,
            "ordered": false,
            "owner": false,
            "identifiableObject": false,
            "nameableObject": false,
            "embeddedObject": false,
            "analyticalObject": false,
            "readable": true,
            "writable": true,
            "unique": false,
            "required": false,
            "max": 1.7976931348623157e308,
            "min": 0,
            "manyToMany": false,
            "oneToOne": false,
            "manyToOne": false,
            "oneToMany": false,
            "translatable": false,
            "gistPreferences": { "included": "AUTO", "transformation": "AUTO" },
            "sortable": false,
            "propertyTransformer": false
        },
        "lastUpdatedBy": {
            "klass": "org.hisp.dhis.user.User",
            "propertyType": "REFERENCE",
            "name": "lastUpdatedBy",
            "fieldName": "lastUpdatedBy",
            "persisted": true,
            "namespace": "http://dhis2.org/schema/dxf/2.0",
            "attribute": false,
            "simple": false,
            "collection": false,
            "ordered": false,
            "owner": true,
            "identifiableObject": true,
            "nameableObject": false,
            "embeddedObject": false,
            "analyticalObject": false,
            "readable": true,
            "writable": true,
            "unique": false,
            "required": false,
            "length": 255,
            "cascade": "none",
            "manyToMany": false,
            "oneToOne": false,
            "manyToOne": true,
            "oneToMany": false,
            "owningRole": "org.hisp.dhis.analytics.AnalyticsTableHook.lastUpdatedBy",
            "href": "http://localhost:8080/api/42/schemas/user",
            "relativeApiEndpoint": "/users",
            "apiEndpoint": "http://localhost:8080/api/42/users",
            "translatable": false,
            "gistPreferences": { "included": "AUTO", "transformation": "AUTO" },
            "sortable": false,
            "propertyTransformer": true
        },
        "access": {
            "klass": "org.hisp.dhis.security.acl.Access",
            "propertyType": "COMPLEX",
            "name": "access",
            "fieldName": "access",
            "persisted": false,
            "namespace": "http://dhis2.org/schema/dxf/2.0",
            "attribute": false,
            "simple": false,
            "collection": false,
            "ordered": false,
            "owner": false,
            "identifiableObject": false,
            "nameableObject": false,
            "embeddedObject": true,
            "analyticalObject": false,
            "readable": true,
            "writable": true,
            "unique": false,
            "required": false,
            "max": 1.7976931348623157e308,
            "min": 0,
            "manyToMany": false,
            "oneToOne": false,
            "manyToOne": false,
            "oneToMany": false,
            "translatable": false,
            "gistPreferences": {
                "included": "FALSE",
                "transformation": "AUTO"
            },
            "sortable": false,
            "propertyTransformer": false
        },
        "code": {
            "klass": "java.lang.String",
            "propertyType": "IDENTIFIER",
            "name": "code",
            "fieldName": "code",
            "persisted": true,
            "description": "The unique code for this Object.",
            "attribute": true,
            "simple": true,
            "collection": false,
            "ordered": false,
            "owner": true,
            "identifiableObject": false,
            "nameableObject": false,
            "embeddedObject": false,
            "analyticalObject": false,
            "readable": true,
            "writable": true,
            "unique": true,
            "required": false,
            "length": 50,
            "max": 50,
            "min": 0,
            "manyToMany": false,
            "oneToOne": false,
            "manyToOne": false,
            "oneToMany": false,
            "translatable": false,
            "gistPreferences": { "included": "AUTO", "transformation": "AUTO" },
            "sortable": true,
            "propertyTransformer": false
        },
        "analyticsTableType": {
            "klass": "org.hisp.dhis.analytics.AnalyticsTableType",
            "propertyType": "CONSTANT",
            "name": "analyticsTableType",
            "fieldName": "analyticsTableType",
            "persisted": true,
            "namespace": "http://dhis2.org/schema/dxf/2.0",
            "attribute": false,
            "simple": true,
            "collection": false,
            "ordered": false,
            "owner": true,
            "identifiableObject": false,
            "nameableObject": false,
            "embeddedObject": false,
            "analyticalObject": false,
            "readable": true,
            "writable": true,
            "unique": false,
            "required": false,
            "length": 50,
            "manyToMany": false,
            "oneToOne": false,
            "manyToOne": false,
            "oneToMany": false,
            "constants": [
                "DATA_VALUE",
                "COMPLETENESS",
                "COMPLETENESS_TARGET",
                "ORG_UNIT_TARGET",
                "VALIDATION_RESULT",
                "EVENT",
                "ENROLLMENT",
                "OWNERSHIP",
                "TRACKED_ENTITY_INSTANCE_EVENTS",
                "TRACKED_ENTITY_INSTANCE_ENROLLMENTS",
                "TRACKED_ENTITY_INSTANCE"
            ],
            "translatable": false,
            "gistPreferences": { "included": "AUTO", "transformation": "AUTO" },
            "sortable": true,
            "propertyTransformer": false
        },
        "displayName": {
            "klass": "java.lang.String",
            "propertyType": "TEXT",
            "name": "displayName",
            "fieldName": "displayName",
            "persisted": false,
            "namespace": "http://dhis2.org/schema/dxf/2.0",
            "attribute": false,
            "simple": true,
            "collection": false,
            "ordered": false,
            "owner": false,
            "identifiableObject": false,
            "nameableObject": false,
            "embeddedObject": false,
            "analyticalObject": false,
            "readable": true,
            "writable": false,
            "unique": false,
            "required": false,
            "manyToMany": false,
            "oneToOne": false,
            "manyToOne": false,
            "oneToMany": false,
            "translatable": false,
            "gistPreferences": { "included": "AUTO", "transformation": "AUTO" },
            "sortable": true,
            "propertyTransformer": false
        },
        "created": {
            "klass": "java.util.Date",
            "propertyType": "DATE",
            "name": "created",
            "fieldName": "created",
            "persisted": true,
            "description": "The date this object was created.",
            "attribute": true,
            "simple": true,
            "collection": false,
            "ordered": false,
            "owner": true,
            "identifiableObject": false,
            "nameableObject": false,
            "embeddedObject": false,
            "analyticalObject": false,
            "readable": true,
            "writable": true,
            "unique": false,
            "required": false,
            "length": 255,
            "manyToMany": false,
            "oneToOne": false,
            "manyToOne": false,
            "oneToMany": false,
            "translatable": false,
            "gistPreferences": { "included": "AUTO", "transformation": "AUTO" },
            "sortable": true,
            "propertyTransformer": false
        },
        "attributeValues": {
            "klass": "org.hisp.dhis.attribute.AttributeValues",
            "propertyType": "COMPLEX",
            "name": "attributeValues",
            "fieldName": "attributeValues",
            "persisted": false,
            "attribute": false,
            "simple": false,
            "collection": false,
            "ordered": false,
            "owner": false,
            "identifiableObject": false,
            "nameableObject": false,
            "embeddedObject": false,
            "analyticalObject": false,
            "readable": true,
            "writable": true,
            "unique": false,
            "required": false,
            "max": 1.7976931348623157e308,
            "min": 0,
            "manyToMany": false,
            "oneToOne": false,
            "manyToOne": false,
            "oneToMany": false,
            "translatable": false,
            "gistPreferences": { "included": "AUTO", "transformation": "AUTO" },
            "sortable": false,
            "propertyTransformer": false
        },
        "sharing": {
            "klass": "org.hisp.dhis.user.sharing.Sharing",
            "propertyType": "COMPLEX",
            "name": "sharing",
            "fieldName": "sharing",
            "persisted": false,
            "namespace": "http://dhis2.org/schema/dxf/2.0",
            "attribute": false,
            "simple": false,
            "collection": false,
            "ordered": false,
            "owner": false,
            "identifiableObject": false,
            "nameableObject": false,
            "embeddedObject": false,
            "analyticalObject": false,
            "readable": true,
            "writable": true,
            "unique": false,
            "required": false,
            "max": 1.7976931348623157e308,
            "min": 0,
            "manyToMany": false,
            "oneToOne": false,
            "manyToOne": false,
            "oneToMany": false,
            "translatable": false,
            "gistPreferences": {
                "included": "FALSE",
                "transformation": "AUTO"
            },
            "sortable": false,
            "propertyTransformer": false
        },
        "sql": {
            "klass": "java.lang.String",
            "propertyType": "TEXT",
            "name": "sql",
            "fieldName": "sql",
            "persisted": true,
            "namespace": "http://dhis2.org/schema/dxf/2.0",
            "attribute": false,
            "simple": true,
            "collection": false,
            "ordered": false,
            "owner": true,
            "identifiableObject": false,
            "nameableObject": false,
            "embeddedObject": false,
            "analyticalObject": false,
            "readable": true,
            "writable": true,
            "unique": false,
            "required": true,
            "length": 2147483647,
            "max": 2147483647,
            "min": 0,
            "manyToMany": false,
            "oneToOne": false,
            "manyToOne": false,
            "oneToMany": false,
            "translatable": false,
            "gistPreferences": { "included": "AUTO", "transformation": "AUTO" },
            "sortable": true,
            "propertyTransformer": false
        },
        "lastUpdated": {
            "klass": "java.util.Date",
            "propertyType": "DATE",
            "name": "lastUpdated",
            "fieldName": "lastUpdated",
            "persisted": true,
            "description": "The date this object was last updated.",
            "attribute": true,
            "simple": true,
            "collection": false,
            "ordered": false,
            "owner": true,
            "identifiableObject": false,
            "nameableObject": false,
            "embeddedObject": false,
            "analyticalObject": false,
            "readable": true,
            "writable": true,
            "unique": false,
            "required": false,
            "length": 255,
            "manyToMany": false,
            "oneToOne": false,
            "manyToOne": false,
            "oneToMany": false,
            "translatable": false,
            "gistPreferences": { "included": "AUTO", "transformation": "AUTO" },
            "sortable": true,
            "propertyTransformer": false
        },
        "createdBy": {
            "klass": "org.hisp.dhis.user.User",
            "propertyType": "REFERENCE",
            "name": "createdBy",
            "fieldName": "createdBy",
            "persisted": false,
            "namespace": "http://dhis2.org/schema/dxf/2.0",
            "attribute": false,
            "simple": false,
            "collection": false,
            "ordered": false,
            "owner": false,
            "identifiableObject": true,
            "nameableObject": false,
            "embeddedObject": false,
            "analyticalObject": false,
            "readable": true,
            "writable": true,
            "unique": false,
            "required": false,
            "manyToMany": false,
            "oneToOne": false,
            "manyToOne": false,
            "oneToMany": false,
            "href": "http://localhost:8080/api/42/schemas/user",
            "relativeApiEndpoint": "/users",
            "apiEndpoint": "http://localhost:8080/api/42/users",
            "translatable": false,
            "gistPreferences": {
                "included": "FALSE",
                "transformation": "AUTO"
            },
            "sortable": false,
            "propertyTransformer": true
        },
        "translations": {
            "klass": "java.util.Set",
            "propertyType": "COLLECTION",
            "itemKlass": "org.hisp.dhis.translation.Translation",
            "itemPropertyType": "COMPLEX",
            "name": "translation",
            "fieldName": "translations",
            "persisted": false,
            "collectionName": "translations",
            "collectionWrapping": true,
            "namespace": "http://dhis2.org/schema/dxf/2.0",
            "attribute": false,
            "simple": false,
            "collection": true,
            "ordered": false,
            "owner": false,
            "identifiableObject": false,
            "nameableObject": false,
            "embeddedObject": false,
            "analyticalObject": false,
            "readable": true,
            "writable": true,
            "unique": false,
            "required": false,
            "max": 1.7976931348623157e308,
            "min": 0,
            "manyToMany": false,
            "oneToOne": false,
            "manyToOne": false,
            "oneToMany": false,
            "translatable": false,
            "gistPreferences": {
                "included": "FALSE",
                "transformation": "AUTO"
            },
            "sortable": false,
            "propertyTransformer": false
        },
        "name": {
            "klass": "java.lang.String",
            "propertyType": "TEXT",
            "name": "name",
            "fieldName": "name",
            "persisted": true,
            "description": "The name of this Object. Required and unique.",
            "attribute": true,
            "simple": true,
            "collection": false,
            "ordered": false,
            "owner": true,
            "identifiableObject": false,
            "nameableObject": false,
            "embeddedObject": false,
            "analyticalObject": false,
            "readable": true,
            "writable": true,
            "unique": true,
            "required": true,
            "length": 255,
            "max": 255,
            "min": 1,
            "manyToMany": false,
            "oneToOne": false,
            "manyToOne": false,
            "oneToMany": false,
            "translatable": false,
            "gistPreferences": { "included": "AUTO", "transformation": "AUTO" },
            "sortable": true,
            "propertyTransformer": false
        },
        "resourceTableType": {
            "klass": "org.hisp.dhis.resourcetable.ResourceTableType",
            "propertyType": "CONSTANT",
            "name": "resourceTableType",
            "fieldName": "resourceTableType",
            "persisted": true,
            "namespace": "http://dhis2.org/schema/dxf/2.0",
            "attribute": false,
            "simple": true,
            "collection": false,
            "ordered": false,
            "owner": true,
            "identifiableObject": false,
            "nameableObject": false,
            "embeddedObject": false,
            "analyticalObject": false,
            "readable": true,
            "writable": true,
            "unique": false,
            "required": false,
            "length": 50,
            "manyToMany": false,
            "oneToOne": false,
            "manyToOne": false,
            "oneToMany": false,
            "constants": [
                "ORG_UNIT_STRUCTURE",
                "DATA_SET_ORG_UNIT_CATEGORY",
                "CATEGORY_OPTION_COMBO_NAME",
                "DATA_ELEMENT_GROUP_SET_STRUCTURE",
                "INDICATOR_GROUP_SET_STRUCTURE",
                "ORG_UNIT_GROUP_SET_STRUCTURE",
                "CATEGORY_STRUCTURE",
                "DATA_ELEMENT_STRUCTURE",
                "DATA_SET",
                "PERIOD_STRUCTURE",
                "DATE_PERIOD_STRUCTURE",
                "DATA_ELEMENT_CATEGORY_OPTION_COMBO",
                "DATA_APPROVAL_REMAP_LEVEL",
                "DATA_APPROVAL_MIN_LEVEL",
                "TEI_RELATIONSHIP_COUNT"
            ],
            "translatable": false,
            "gistPreferences": { "included": "AUTO", "transformation": "AUTO" },
            "sortable": true,
            "propertyTransformer": false
        },
        "uid": {
            "klass": "java.lang.String",
            "propertyType": "IDENTIFIER",
            "name": "id",
            "fieldName": "uid",
            "persisted": true,
            "description": "The Unique Identifier for this Object.",
            "attribute": true,
            "simple": true,
            "collection": false,
            "ordered": false,
            "owner": true,
            "identifiableObject": false,
            "nameableObject": false,
            "embeddedObject": false,
            "analyticalObject": false,
            "readable": true,
            "writable": true,
            "unique": true,
            "required": false,
            "length": 11,
            "max": 11,
            "min": 11,
            "manyToMany": false,
            "oneToOne": false,
            "manyToOne": false,
            "oneToMany": false,
            "translatable": false,
            "gistPreferences": { "included": "AUTO", "transformation": "AUTO" },
            "sortable": true,
            "propertyTransformer": false
        },
        "href": {
            "klass": "java.lang.String",
            "propertyType": "URL",
            "name": "href",
            "fieldName": "href",
            "persisted": false,
            "attribute": true,
            "simple": true,
            "collection": false,
            "ordered": false,
            "owner": false,
            "identifiableObject": false,
            "nameableObject": false,
            "embeddedObject": false,
            "analyticalObject": false,
            "readable": true,
            "writable": true,
            "unique": false,
            "required": false,
            "max": 1.7976931348623157e308,
            "min": 0,
            "manyToMany": false,
            "oneToOne": false,
            "manyToOne": false,
            "oneToMany": false,
            "translatable": false,
            "gistPreferences": { "included": "AUTO", "transformation": "AUTO" },
            "sortable": false,
            "propertyTransformer": false
        },
        "favorite": {
            "klass": "java.lang.Boolean",
            "propertyType": "BOOLEAN",
            "name": "favorite",
            "fieldName": "favorite",
            "persisted": false,
            "namespace": "http://dhis2.org/schema/dxf/2.0",
            "attribute": false,
            "simple": true,
            "collection": false,
            "ordered": false,
            "owner": false,
            "identifiableObject": false,
            "nameableObject": false,
            "embeddedObject": false,
            "analyticalObject": false,
            "readable": true,
            "writable": false,
            "unique": false,
            "required": false,
            "manyToMany": false,
            "oneToOne": false,
            "manyToOne": false,
            "oneToMany": false,
            "translatable": false,
            "gistPreferences": { "included": "AUTO", "transformation": "AUTO" },
            "sortable": false,
            "propertyTransformer": false
        },
        "user": {
            "klass": "org.hisp.dhis.user.User",
            "propertyType": "REFERENCE",
            "name": "user",
            "fieldName": "user",
            "persisted": false,
            "namespace": "http://dhis2.org/schema/dxf/2.0",
            "attribute": false,
            "simple": false,
            "collection": false,
            "ordered": false,
            "owner": false,
            "identifiableObject": true,
            "nameableObject": false,
            "embeddedObject": false,
            "analyticalObject": false,
            "readable": true,
            "writable": true,
            "unique": false,
            "required": false,
            "manyToMany": false,
            "oneToOne": false,
            "manyToOne": false,
            "oneToMany": false,
            "href": "http://localhost:8080/api/42/schemas/user",
            "relativeApiEndpoint": "/users",
            "apiEndpoint": "http://localhost:8080/api/42/users",
            "translatable": false,
            "gistPreferences": { "included": "AUTO", "transformation": "AUTO" },
            "sortable": false,
            "propertyTransformer": true
        }
    },
    "translatable": false
}
